eyws/__init__.py
eyws/about.py
eyws/docker.py
eyws/parser.py
eyws/ssh.py
eyws-1.0.0b5.dist-info/LICENSE.txt
eyws-1.0.0b5.dist-info/METADATA
eyws-1.0.0b5.dist-info/RECORD
eyws-1.0.0b5.dist-info/WHEEL
eyws-1.0.0b5.dist-info/entry_points.txt
eyws-1.0.0b5.dist-info/top_level.txt
