Metadata-Version: 2.1
Name: eyws
Version: 1.0.0b5
Summary: Daily use alternate AWS CLI
Home-page: https://github.com/canelmas/eyws
Author: Can Elmas
Author-email: canelm@gmail.com
License: Apache License 2.0
Keywords: aws cli
Platform: UNKNOWN
Classifier: Development Status :: 4 - Beta
Classifier: Intended Audience :: Developers
Classifier: Intended Audience :: System Administrators
Classifier: License :: OSI Approved :: Apache Software License
Classifier: Natural Language :: English
Classifier: Operating System :: POSIX :: Linux
Classifier: Operating System :: MacOS :: MacOS X
Classifier: Operating System :: Microsoft :: Windows
Classifier: Programming Language :: Python :: 3.1
Classifier: Programming Language :: Python :: 3.2
Classifier: Programming Language :: Python :: 3.3
Classifier: Programming Language :: Python :: 3.4
Classifier: Programming Language :: Python :: 3.5
Classifier: Programming Language :: Python :: 3.6
Classifier: Programming Language :: Python :: 3.7
Classifier: Topic :: Software Development :: Libraries :: Python Modules
Classifier: Topic :: Utilities
Requires-Python: >=3.1
Requires-Dist: jinja2 (>=2.10)
Requires-Dist: python-dateutil (>=2.7.3)
Requires-Dist: boto3 (==1.8.1)
Requires-Dist: botocore (==1.11.1)
